pyrobot/indicators.py
pyrobot/portfolio.py
pyrobot/robot.py
pyrobot/stock_frame.py
pyrobot/trades.py
samples/trading_robot.py
samples/trading_robot_indicators.py
samples/trading_robot_indicators_compare.py
tests/test_indicators.py
tests/test_portfolio.py
tests/test_robot.py
tests/test_stock_frame.py
tests/test_trades.py
python_trading_robot-0.1.1.dist-info/LICENSE
python_trading_robot-0.1.1.dist-info/METADATA
python_trading_robot-0.1.1.dist-info/WHEEL
python_trading_robot-0.1.1.dist-info/top_level.txt
python_trading_robot-0.1.1.dist-info/RECORD
