Metadata-Version: 2.1
Name: python-trading-robot
Version: 0.1.1
Summary: A trading robot built for Python that uses the TD Ameritrade API.
Home-page: https://github.com/areed1192/python-trading-robot
Author: Alex Reed
Author-email: coding.sigma@gmail.com
License: UNKNOWN
Keywords: finance,td ameritrade,api,trading robot
Platform: UNKNOWN
Classifier: Development Status :: 3 - Alpha
Classifier: Intended Audience :: Developers
Classifier: Intended Audience :: Science/Research
Classifier: Intended Audience :: Financial and Insurance Industry
Classifier: License :: OSI Approved :: MIT License
Classifier: Natural Language :: English
Classifier: Operating System :: OS Independent
Classifier: Programming Language :: Python
Classifier: Programming Language :: Python :: 3
Classifier: Programming Language :: Python :: 3.8
Classifier: Topic :: Database
Classifier: Topic :: Education
Classifier: Topic :: Office/Business
Requires-Python: >=3.8
Requires-Dist: td-ameritrade-python-api (==0.3.0)
Requires-Dist: pandas (==1.0.5)
Requires-Dist: numpy (==1.19.0)
